CryptoPriceBIN/CryptoPriceBIN.py
CryptoPriceBIN/__init__.py
CryptoPriceBIN/scrapper.py
CryptoPriceBIN-1.0.0.dist-info/LICENSE
CryptoPriceBIN-1.0.0.dist-info/METADATA
CryptoPriceBIN-1.0.0.dist-info/WHEEL
CryptoPriceBIN-1.0.0.dist-info/top_level.txt
CryptoPriceBIN-1.0.0.dist-info/RECORD
