Metadata-Version: 2.1
Name: CryptoPriceBIN
Version: 1.0.0
Summary: A Python Module that gives us current Crypto Prices
Home-page: https://github.com/DeKabilan/crypto_price_module
Author: DeKabilan
Author-email: dekabilanmc@gmail.com
Project-URL: Bug Tracker, https://github.com/DeKabilan/crypto_price_module/issues
Classifier: Programming Language :: Python :: 3
Classifier: License :: OSI Approved :: MIT License
Classifier: Operating System :: OS Independent
Requires-Python: >=3.6
License-File: LICENSE
